LICENSE
MANIFEST.in
README.md
README.rst
setup.py
zqifatools/__init__.py
zqifatools/__version__.py
zqifatools/core.py
zqifatools.egg-info/PKG-INFO
zqifatools.egg-info/SOURCES.txt
zqifatools.egg-info/dependency_links.txt
zqifatools.egg-info/top_level.txt