Metadata-Version: 1.2
Name: zqifatools
Version: 0.0.1
Summary: tools
Home-page: https://github.com/zqifa
Author: Aaron Chu
Author-email: zqifa@outlook.com
Maintainer: aaron
Maintainer-email: zqifa@outlook.com
License: BSD License
Platform: all
Classifier: Development Status :: 4 - Beta
Classifier: Operating System :: OS Independent
Classifier: Intended Audience :: Developers
Classifier: License :: OSI Approved :: BSD License
Classifier: Programming Language :: Python
Classifier: Programming Language :: Python :: 2.7
Classifier: Programming Language :: Python :: Implementation :: CPython
Classifier: Programming Language :: Python :: Implementation :: PyPy
